ethiack_cli/__init__.py
ethiack_cli/__main__.py
ethiack_cli/ethiack.py
ethiack_cli-1.0.0.dist-info/LICENSE
ethiack_cli-1.0.0.dist-info/METADATA
ethiack_cli-1.0.0.dist-info/WHEEL
ethiack_cli-1.0.0.dist-info/entry_points.txt
ethiack_cli-1.0.0.dist-info/top_level.txt
ethiack_cli-1.0.0.dist-info/RECORD
