Metadata-Version: 2.1
Name: ethiack-cli
Version: 1.0.0
Summary: Ethiack API Utility
Home-page: https://github.com/fssecur3/ethiack-cli
Project-URL: Bug Tracker, https://github.com/fssecur3/ethiack-cli
Project-URL: Changelog, https://github.com/fssecur3/ethiack-cli
Classifier: Programming Language :: Python :: 3
Classifier: License :: OSI Approved :: BSD License
Classifier: Intended Audience :: Developers
Requires-Python: >=3.10
License-File: LICENSE
